closest-0.2.0.dist-info/METADATA
closest-0.2.0.dist-info/WHEEL
closest-0.2.0.dist-info/licenses/LICENSE.md
closest/py.typed
closest/__init__.py
closest/closest.cpython-38-i386-linux-gnu.so
closest-0.2.0.dist-info/RECORD
