Metadata-Version: 2.4
Name: closest
Version: 0.2.0
Classifier: Programming Language :: Rust
Classifier: Programming Language :: Python :: Implementation :: CPython
Classifier: Programming Language :: Python :: Implementation :: PyPy
Requires-Dist: pytest ; extra == 'tests'
Requires-Dist: version ; extra == 'dynamic'
Provides-Extra: tests
Provides-Extra: dynamic
License-File: LICENSE.md
Summary: Nearest neighbors implementation written in rust.
Author: James Inlow
Requires-Python: >=3.8
